{
    "type": "minecraft:generic",
    "pools": [
        {
            "rolls": 1,
            "entries": [
                {
                    "type": "minecraft:item",
                    "name": "minecraft:carrot_on_a_stick",
                    "functions": [
                        {
                            "function": "minecraft:set_count",
                            "count": 1
                        },
                        {
                            "function": "minecraft:set_nbt",
                            "tag": "{mie_id:\"magic_shears\",CustomModelData:13950400,RepairCost:999}"
                        },
                        {
                            "function": "minecraft:set_name",
                            "name": {"translate":"item.mie.name.shears"}
                        },
                        {
                            "function": "minecraft:set_lore",
                            "lore": [
                                {"translate":"item.mie.lore0.shears"},
                                {"translate":"item.mie.lore1.shears"},
                                {"translate":"item.mie.lore2.shears"}
                            ]
                        }
                    ]
                }
            ]
        }
    ]
}